geometry_lib/__init__.py
geometry_lib/shapes/__init__.py
geometry_lib/shapes/base.py
geometry_lib/shapes/factory.py
geometry_lib/shapes/primitives.py
geometry_lib/utils/__init__.py
geometry_lib/utils/validators.py
geometry_lib_pca-1.0.4.dist-info/LICENSE
geometry_lib_pca-1.0.4.dist-info/METADATA
geometry_lib_pca-1.0.4.dist-info/WHEEL
geometry_lib_pca-1.0.4.dist-info/RECORD
