Metadata-Version: 2.1
Name: geometry-lib-pca
Version: 1.0.4
Summary: A library for geometric computations (for didactic purposes only).
License: MIT
Author: Gabriel Machado
Author-email: gabriel.rmachado10@gmail.com
Requires-Python: >=3.9,<4.0
Classifier: License :: OSI Approved :: MIT License
Classifier: Programming Language :: Python :: 3
Classifier: Programming Language :: Python :: 3.9
Classifier: Programming Language :: Python :: 3.10
Classifier: Programming Language :: Python :: 3.11
Classifier: Programming Language :: Python :: 3.12
